safe_unzip/__init__.py
safe_unzip/__init__.pyi
safe_unzip/__main__.py
safe_unzip/_safe_unzip.cpython-311-x86_64-linux-gnu.so
safe_unzip/py.typed
safe_unzip-0.1.6.dist-info/METADATA
safe_unzip-0.1.6.dist-info/WHEEL
safe_unzip-0.1.6.dist-info/RECORD
