Metadata-Version: 2.4
Name: safe-unzip
Version: 0.1.6
Classifier: Programming Language :: Rust
Classifier: Programming Language :: Python :: Implementation :: CPython
Classifier: Programming Language :: Python :: 3
Classifier: Programming Language :: Python :: 3.8
Classifier: Programming Language :: Python :: 3.9
Classifier: Programming Language :: Python :: 3.10
Classifier: Programming Language :: Python :: 3.11
Classifier: Programming Language :: Python :: 3.12
Classifier: Programming Language :: Python :: 3.13
Classifier: Programming Language :: Python :: 3.14
Classifier: Topic :: Security
Classifier: Topic :: System :: Archiving :: Compression
Summary: Secure zip extraction. Prevents Zip Slip and Zip Bombs.
Keywords: zip,security,archive,extraction,safe,zip-slip,zip-bomb
Author-email: "Niki A." <dev@tenuo.dev>
License: MIT OR Apache-2.0
Requires-Python: >=3.8
Project-URL: Homepage, https://github.com/tenuo-ai/safe_unzip
Project-URL: Repository, https://github.com/tenuo-ai/safe_unzip
